Metadata-Version: 2.1
Name: fastapi-router-controller
Version: 0.4.1
Summary: A FastAPI utility to allow Controller Class usage
Home-page: https://github.com/KiraPC/fastapi-router-controller
Author: Pasquale Carmine Carbone
Author-email: pasqualecarmine.carbone@gmail.com
License: UNKNOWN
Platform: UNKNOWN
Classifier: Programming Language :: Python :: 3
Classifier: License :: OSI Approved :: MIT License
Classifier: Operating System :: OS Independent
Classifier: Topic :: Software Development :: Libraries :: Python Modules
Classifier: Topic :: Software Development :: Libraries
Classifier: Topic :: Software Development
Classifier: Typing :: Typed
Requires-Python: >=3.6
Provides-Extra: tests
